compgraph2txt/__init__.py
compgraph2txt/_impl.py
compgraph2txt/tests/__init__.py
compgraph2txt/tests/test_compgraph2txt.py
compgraph2txt-1.0.0.dist-info/METADATA
compgraph2txt-1.0.0.dist-info/WHEEL
compgraph2txt-1.0.0.dist-info/licenses/LICENSE.md
compgraph2txt-1.0.0.dist-info/RECORD
